{
    "version": 2,
    "sources": {
        "narwhal": {
            "type": "github",
            "user": "280north"
        },
        "narwhal-jsc": {
            "type": "github",
            "user": "280north"
        },
        "narwhal-v8": {
            "type": "github",
            "user": "tlrobinson"
        },
        "narwhal-v8cgi": {
            "type": "github",
            "user": "veged"
        },
        "narwhal-johnson": {
            "type": "github",
            "user": "tlrobinson"
        },
        "narwhal-xulrunner": {
            "type": "github",
            "user": "Gozala"
        },
        "narwhal-jaxer": {
            "type": "github",
            "user": "smith"
        },
        "narwhal-moar-monkeys": {
            "type": "github",
            "user": "kriskowal"
        },
        "jack": {
            "type": "github",
            "user": "280north"
        },
        "nitro": {
            "type": "github",
            "user": "gmosx"
        },
        "chiron": {
            "type": "github",
            "user": "kriskowal"
        },
        "narcissus": {
            "type": "github",
            "user": "andychu"
        },
        "creolejs": {
            "type": "github",
            "user": "kriskowal"
        },
        "browserjs": {
            "type": "github",
            "user": "280north"
        },
        "inspec": {
            "type": "github",
            "user": "aq1018"
        },
        "kupo": {
            "type": "github",
            "user": "janv"
        },
        "appengine": {
            "type": "github",
            "user": "gmosx"
        },
        "jack-servlet": {
            "type": "github",
            "user": "tlrobinson"
        },
        "appengine-java-sdk": {
            "type": "inline",
            "descriptor": {
                "name": "appengine-java-sdk",
                "title": "Google App Engine Java SDK",
                "description": "Java components necessary for deploying applications on Google's App Engine.",
                "author": "Google",
                "version": "1.3.0",
                "dependencies": ["jack-servlet", "jack", "narwhal"],
                "lib": [],
                "type": "zip",
                "packageUrl": "http://googleappengine.googlecode.com/files/appengine-java-sdk-1.3.0.zip"
            }
        },
        "env": {
            "type": "github",
            "name": "env-js",
            "user": "kriskowal",
            "descriptor": {}
        },
        "template": {
            "type": "github",
            "user": "gmosx"
        },
        "markdown": {
            "type": "github",
            "user": "gmosx"
        },
        "xbin": {
            "type": "github",
            "user": "kriskowal"
        },
        "wiky": {
            "type": "github",
            "user": "kriskowal"
        },
        "jsdocs": {
            "type": "github",
            "user": "Gozala"
        },
        "syntax-stroop": {
            "type": "github",
            "user": "Gozala"
        },
        "seethrough": {
            "type": "github",
            "user": "Gozala"
        },
        "jack-dav": {
            "type": "github",
            "user": "tlrobinson"
        },
        "jsont": {
            "type": "github",
            "user": "tlrobinson"
        },
        "activejs": {
            "type": "github",
            "user": "tlrobinson",
            "ref": "package"
        },
        "speller": {
            "type": "github",
            "user": "past"
        },
        "jake": {
            "type": "github",
            "user": "280north"
        },
        "json-rpc": {
            "type": "github",
            "user": "tlrobinson"
        },
        "prototype": {
            "type": "github",
            "name": "prototype-asp",
            "user": "smith",
            "ref": "narwhal-global"
        },
        "qunit": {
            "type": "github",
            "user": "jquery"
        },
        "oauth": {
            "type": "github",
            "user": "cloudwork"
        },
        "bogart": {
            "type": "github",
            "user": "nrstott"
        },
        "json-template": {
            "type": "github",
            "user": "andychu"
        },
        "ejs": {
            "type": "github",
            "user": "nrstott",
            "name": "narwhal-ejs"
        },
        "couchdb": {
            "type": "github",
            "user": "nrstott",
            "name": "narwhal-couchdb"
        },
        "mongodb": {
            "type": "github",
            "user": "mrclash",
            "name": "narwhal-mongodb"
        },
        "underscore": {
            "type": "github",
            "user": "kriskowal"
        },
        "silk": {
            "type": "github",
            "user": "kriskowal"
        },
        "objective-j": {
            "type": "github",
            "user": "280north",
            "name": "objective-j-package"
        },
        "cappuccino": {
            "type": "github",
            "user": "280north",
            "name": "cappuccino-package"
        },
        "ojunit": {
            "type": "github",
            "user": "280north"
        },
        "qxoo": {
            "type": "github",
            "user": "fjakobs",
            "name": "qxoo"
        },
        "barista": {
            "type": "github",
            "user": "hammerdr"
        },
        "ojmoq": {
            "type": "github",
            "user": "hammerdr"
        },
        "sizzle": {
            "type": "github",
            "user": "gmosx"
        },
        "observable": {
            "type": "github",
            "user": "nrstott",
            "name": "observable-js"
        },
        "commonjs-utils": {
            "type": "github",
            "user": "kriszyp",
            "name": "commonjs-utils"
        },
        "cappruby": {
            "type": "github",
            "user": "tlrobinson"
        },
        "coffee-script": {
            "type": "github",
            "user": "tlrobinson"
        },
        "parenscript": {
            "type": "github",
            "user": "fitzgen",
            "name": "parenscript-narwhal"
        },
        "jaml": {
            "type": "github",
            "user": "tlrobinson"
        },
        "jscrypto": {
            "type": "github",
            "user": "tlrobinson"
        },
        "narwhal-v8cgi": {
            "type": "github",
            "user": "veged"
        },
        "CappuccinoResource": {
            "type": "github",
            "user": "sant0sk1"
        },
        "yuicompressor": {
            "type": "github",
            "user": "280north",
            "name": "commonjs-yuicompressor"
        },
        "shmakowiki": {
            "type": "github",
            "user": "veged",
            "ref": "narwhal"
        },
        "ometajs": {
            "type": "github",
            "user": "veged",
            "name": "ometa-js",
            "ref": "narwhal"
        },
        "ometa-highlighter": {
            "type": "github",
            "user": "veged",
            "ref": "narwhal"
        },
        "closure-compiler": {
            "type": "github",
            "user": "280north",
            "name": "commonjs-closure-compiler"
        },
        "yuicompressor": {
            "type": "github",
            "user": "280north",
            "name": "commonjs-yuicompressor"
        },
        "shrinksafe": {
            "type": "github",
            "user": "280north",
            "name": "commonjs-shrinksafe"
        },
        "haml-js": {
            "type": "github",
            "user": "creationix"
        },
        "mustache": {
            "type": "github",
            "user": "tlrobinson",
            "name": "mustache.js"
        },
        "htmlparser": {
            "type": "github",
            "user": "gmosx",
            "name": "htmlparser"
        },
        "normal-template": {
            "type": "github",
            "user": "gmosx",
            "name": "normal-template"
        },
        "reform": {
            "type": "github",
            "user": "fitzgen"
        },
        "jdbc": {
            "type": "github",
            "user": "tlrobinson",
            "name": "commonjs-jdbc"
        },
        "mysql-jdbc": {
            "type": "github",
            "user": "tlrobinson",
            "name": "commonjs-mysql-jdbc"
        },
        "sqlite-jdbc": {
            "type": "github",
            "user": "tlrobinson",
            "name": "commonjs-sqlite-jdbc"
        }
    }
}
